keycardai/__init__.py
keycardai-0.2.0.dist-info/METADATA
keycardai-0.2.0.dist-info/WHEEL
keycardai-0.2.0.dist-info/licenses/LICENSE
keycardai-0.2.0.dist-info/RECORD
