Metadata-Version: 2.4
Name: keycardai
Version: 0.2.0
Summary: Keycard Python SDK - A workspace for Keycard service packages
Project-URL: Homepage, https://github.com/keycardai/python-sdk
Project-URL: Documentation, https://docs.keycardai.com
Project-URL: Repository, https://github.com/keycardai/python-sdk
Project-URL: Issues, https://github.com/keycardai/python-sdk/issues
Author-email: KeycardAI <support@keycardai.com>
License: MIT
License-File: LICENSE
Keywords: api,authentication,keycard,oauth,security
Classifier: Development Status :: 3 - Alpha
Classifier: Intended Audience :: Developers
Classifier: License :: OSI Approved :: MIT License
Classifier: Programming Language :: Python :: 3
Classifier: Programming Language :: Python :: 3.10
Classifier: Programming Language :: Python :: 3.11
Classifier: Programming Language :: Python :: 3.12
Classifier: Topic :: Internet :: WWW/HTTP
Classifier: Topic :: Security
Classifier: Topic :: Software Development :: Libraries :: Python Modules
Requires-Python: >=3.10
Provides-Extra: dev
Requires-Dist: black>=24.12.0; extra == 'dev'
Requires-Dist: commitizen>=3.29.0; extra == 'dev'
Requires-Dist: isort>=5.13.2; extra == 'dev'
Requires-Dist: mypy>=1.14.1; extra == 'dev'
Requires-Dist: pre-commit>=4.3.0; extra == 'dev'
Requires-Dist: pytest-cov>=6.2.1; extra == 'dev'
Requires-Dist: pytest>=8.4.1; extra == 'dev'
Requires-Dist: ruff>=0.12.10; extra == 'dev'
